./.gitignore
./PKG-INFO
./README.md
./pyproject.toml
./server.py
./.github/workflows/publish.yml
mcp_server_mql5-0.1.2.dist-info/METADATA
mcp_server_mql5-0.1.2.dist-info/WHEEL
mcp_server_mql5-0.1.2.dist-info/entry_points.txt
mcp_server_mql5-0.1.2.dist-info/RECORD
