Metadata-Version: 2.4
Name: mcp-server-mql5
Version: 0.1.2
Summary: A MCP server for MQL5 development: Compiles code locally via MetaEditor and searches official docs.
Requires-Python: >=3.10
Requires-Dist: beautifulsoup4>=4.12.0
Requires-Dist: mcp>=0.1.0
Requires-Dist: requests>=2.31.0
